{
  "sections": {
    "hot_products": {
      "type": "product-list",
      "blocks": {
        "product_header": {
          "type": "text",
          "settings": {
            "text": "<h2>HOT NOW</h2>",
            "alignment": "center",
            "type_preset": "h2",
            "case": "uppercase"
          }
        }
      },
      "block_order": ["product_header"],
      "settings": {
        "collection": "all",
        "layout_type": "grid",
        "max_products": 16,
        "columns": 4,
        "mobile_columns": "2",
        "color_scheme": "scheme-1",
        "padding-block-start": 60,
        "padding-block-end": 80
      }
    },
    "collections_section": {
      "type": "collection-list",
      "blocks": {
        "header_group": {
          "type": "group",
          "settings": {
            "content_direction": "column",
            "horizontal_alignment": "center",
            "gap": 16,
            "width": "fill"
          },
          "blocks": {
            "heading": {
              "type": "text",
              "settings": {
                "text": "<h2>COLLECTIONS</h2>",
                "alignment": "center",
                "type_preset": "h2",
                "case": "uppercase"
              }
            }
          },
          "block_order": ["heading"]
        }
      },
      "block_order": ["header_group"],
      "settings": {
        "collection_list": [],
        "layout_type": "grid",
        "columns": 4,
        "mobile_columns": "2",
        "columns_gap": 16,
        "rows_gap": 16,
        "section_width": "page-width",
        "gap": 32,
        "color_scheme": "scheme-1",
        "padding-block-start": 80,
        "padding-block-end": 80
      }
    },
    "best_sellers": {
      "type": "product-list",
      "blocks": {
        "product_header": {
          "type": "text",
          "settings": {
            "text": "<h2>BEST SELLERS</h2>",
            "alignment": "center",
            "type_preset": "h2",
            "case": "uppercase"
          }
        }
      },
      "block_order": ["product_header"],
      "settings": {
        "collection": "all",
        "layout_type": "grid",
        "max_products": 8,
        "columns": 4,
        "mobile_columns": "2",
        "color_scheme": "scheme-2",
        "padding-block-start": 80,
        "padding-block-end": 80
      }
    },
    "instagram_feed": {
      "type": "section",
      "blocks": {
        "instagram_header": {
          "type": "text",
          "settings": {
            "text": "<h2>INSTAGRAM POSTS</h2><p>@aniqi.studios</p>",
            "alignment": "center",
            "type_preset": "h2",
            "case": "uppercase"
          }
        }
      },
      "block_order": ["instagram_header"],
      "settings": {
        "content_direction": "column",
        "horizontal_alignment": "center",
        "gap": 20,
        "color_scheme": "scheme-1",
        "padding-block-start": 80,
        "padding-block-end": 80
      }
    },
    "newsletter_signup": {
      "type": "section",
      "blocks": {
        "newsletter_header": {
          "type": "text",
          "settings": {
            "text": "<h2>JOIN OUR FAMILY!</h2><p>Sign up to our newsletter and receive special discount on your first order.</p>",
            "alignment": "center",
            "type_preset": "h2",
            "case": "uppercase"
          }
        }
      },
      "block_order": ["newsletter_header"],
      "settings": {
        "content_direction": "column",
        "horizontal_alignment": "center",
        "gap": 20,
        "color_scheme": "scheme-3",
        "padding-block-start": 80,
        "padding-block-end": 80
      }
    }
  },
  "order": [
    "hot_products",
    "collections_section",
    "best_sellers",
    "instagram_feed",
    "newsletter_signup"
  ]
}